{
    "class": "DepictionTabView",
    "headerImage": "https://yandevelop.github.io/assets/imgs/Anouk/banner.png",
    "tabs": [{
            "class": "DepictionStackView",
            "tabname": "Overview",
            "views": [{
                    "itemCornerRadius": 4,
                    "class": "DepictionScreenshotsView",
                    "itemSize": "{160, 275.41333333333336}",
                    "screenshots": [
                        {
                            "accessibilityText": "Anouk screenshot",
                            "url": "https://yandevelop.github.io/assets/imgs/Anouk/AnoukScreen1.png"
                        },
                        {
                            "accessibilityText": "Anouk screenshot 2",
                            "url": "https://yandevelop.github.io/assets/imgs/Anouk/AnoukScreen2.png"
                        }
                    ]
                },
                {
                    "class": "DepictionSpacerView",
                    "spacing": 9
                },
                {   
                    "class": "DepictionHeaderView",
                    "title": "Description",
                    "useBoldText": true
                },
                {
                    "class": "DepictionMarkdownView",
                    "markdown": "Authentication layer for the hidden album."
                },
                {
                    "class": "DepictionSeparatorView"
                },
                {   
                    "class": "DepictionHeaderView",
                    "title": "Details",
                    "useBoldText": true
                },
                {
                    "title": "Latest Version",
                    "text": "1.1",
                    "class": "DepictionTableTextView"
                },
                {   
                    "class": "DepictionTableTextView",
                    "title": "Compatibility",
                    "text": "iOS 13 - 16.4.1"
                },
                {   
                    "class": "DepictionTableTextView",
                    "title": "Supported Devices",
                    "text": "iPhone, iPad"
                },
                {
                    "class": "DepictionSpacerView",
                    "spacing": 9
                },
                {
                    "class": "DepictionTableButtonView",
                    "title": "Follow me on Twitter",
                    "action": "https://twitter.com/yandevelop"
                },
                {
                    "class": "DepictionTableButtonView",
                    "title": "Donate",
                    "action": "https://paypal.me/JanSchweikert04"
                },
                {
                    "class": "DepictionTableButtonView",
                    "title": "Changelog",
                    "action": "https://yandevelop.github.io/depic/Anouk/changelog.html"
                },
                {
                    "class": "DepictionSpacerView",
                    "spacing": 9
                }
            ]
        }
    ],
    "minVersion": "0.1"
}
